oriole_test/__init__.py
oriole_test/cli.py
oriole_test/oriole_test.py
oriole_test-0.8.0.dist-info/DESCRIPTION.rst
oriole_test-0.8.0.dist-info/METADATA
oriole_test-0.8.0.dist-info/RECORD
oriole_test-0.8.0.dist-info/WHEEL
oriole_test-0.8.0.dist-info/entry_points.txt
oriole_test-0.8.0.dist-info/metadata.json
oriole_test-0.8.0.dist-info/top_level.txt
