Metadata-Version: 2.0
Name: oriole-test
Version: 0.8.0
Summary: Support tdd for oriole-service.
Home-page: https://github.com/zhouxiaoxiang/oriole-test
Author: Eric.Zhou
Author-email: xiaoxiang.cn@gmail.com
License: MIT license
Keywords: oriole-test
Platform: UNKNOWN
Classifier: Development Status :: 2 - Pre-Alpha
Classifier: Intended Audience :: Developers
Classifier: License :: OSI Approved :: MIT License
Classifier: Natural Language :: English
Classifier: Programming Language :: Python :: 3.6
Requires-Dist: Click (>=6.0)
Requires-Dist: oriole (>=7.1.0)
